{"variants":{"color=black":{"model":"paintingmod:black_brick"},"color=red":{"model":"paintingmod:red_brick"},"color=green":{"model":"paintingmod:green_brick"},"color=brown":{"model":"paintingmod:brown_brick"},"color=blue":{"model":"paintingmod:blue_brick"},"color=purple":{"model":"paintingmod:purple_brick"},"color=cyan":{"model":"paintingmod:cyan_brick"},"color=light_gray":{"model":"paintingmod:light_gray_brick"},"color=gray":{"model":"paintingmod:gray_brick"},"color=pink":{"model":"paintingmod:pink_brick"},"color=lime":{"model":"paintingmod:lime_brick"},"color=yellow":{"model":"paintingmod:yellow_brick"},"color=light_blue":{"model":"paintingmod:light_blue_brick"},"color=magenta":{"model":"paintingmod:magenta_brick"},"color=orange":{"model":"paintingmod:orange_brick"},"color=white":{"model":"paintingmod:white_brick"}}}